setup.py
cssgrid/__init__.py
cssgrid/makotemplates.py
cssgrid.egg-info/PKG-INFO
cssgrid.egg-info/SOURCES.txt
cssgrid.egg-info/dependency_links.txt
cssgrid.egg-info/not-zip-safe
cssgrid.egg-info/requires.txt
cssgrid.egg-info/top_level.txt