Metadata-Version: 1.0
Name: cssgrid
Version: 0.1
Summary: Css grid wrapper for use in templating.
Home-page: UNKNOWN
Author: Ian Wilson
Author-email: ian@laspilitas.com
License: BSD
Platform: UNKNOWN
Classifier: Development Status :: 3 - Alpha
Classifier: Topic :: Utilities
Classifier: License :: OSI Approved :: BSD License
